MindsporeTrainer/__init__.py
MindsporeTrainer/launcher.py
MindsporeTrainer/apps/__init__.py
MindsporeTrainer/apps/models/__init__.py
MindsporeTrainer/apps/models/classify.py
MindsporeTrainer/apps/models/resnet.py
MindsporeTrainer/apps/tasks/__init__.py
MindsporeTrainer/apps/tasks/bert.py
MindsporeTrainer/apps/tasks/bleu.py
MindsporeTrainer/apps/tasks/deberta.py
MindsporeTrainer/apps/tasks/gjc.py
MindsporeTrainer/apps/tasks/ms_resnet_task.py
MindsporeTrainer/apps/tasks/record_eval.py
MindsporeTrainer/data/__init__.py
MindsporeTrainer/data/async_data.py
MindsporeTrainer/data/dynamic_dataset.py
MindsporeTrainer/data/example.py
MindsporeTrainer/modeling/__init__.py
MindsporeTrainer/modeling/bert_tokenizer.py
MindsporeTrainer/modeling/config.py
MindsporeTrainer/modeling/file_utils.py
MindsporeTrainer/modeling/gpt2_bpe_utils.py
MindsporeTrainer/modeling/gpt2_tokenizer.py
MindsporeTrainer/modeling/layers.py
MindsporeTrainer/modeling/loss.py
MindsporeTrainer/modeling/modeling_adapter.py
MindsporeTrainer/modeling/models.py
MindsporeTrainer/modeling/msops.py
MindsporeTrainer/modeling/resnet.py
MindsporeTrainer/modeling/spm_tokenizer.py
MindsporeTrainer/modeling/tokenizers.py
MindsporeTrainer/modeling/vgg.py
MindsporeTrainer/modeling/weight_init.py
MindsporeTrainer/modeling/transformer/__init__.py
MindsporeTrainer/modeling/transformer/layers.py
MindsporeTrainer/modeling/transformer/loss.py
MindsporeTrainer/modeling/transformer/moe.py
MindsporeTrainer/modeling/transformer/op_parallel_config.py
MindsporeTrainer/modeling/transformer/transformer.py
MindsporeTrainer/optims/__init__.py
MindsporeTrainer/optims/adam.py
MindsporeTrainer/optims/args.py
MindsporeTrainer/optims/lr_schedulers.py
MindsporeTrainer/optims/utils.py
MindsporeTrainer/task/__init__.py
MindsporeTrainer/task/task.py
MindsporeTrainer/task/task_registry.py
MindsporeTrainer/training/__init__.py
MindsporeTrainer/training/_utils.py
MindsporeTrainer/training/args.py
MindsporeTrainer/training/model_for_GAN.py
MindsporeTrainer-0.2.0.dist-info/LICENSE
MindsporeTrainer-0.2.0.dist-info/METADATA
MindsporeTrainer-0.2.0.dist-info/WHEEL
MindsporeTrainer-0.2.0.dist-info/top_level.txt
MindsporeTrainer-0.2.0.dist-info/RECORD
