Metadata-Version: 2.1
Name: MindsporeTrainer
Version: 0.2.0
Summary: Make Mindspore Training Easier
Home-page: https://github.com/baudzhou/MindsporeTrainer
Author: Zhou Bo
Author-email: baudzhou@outlook.com
License: MIT
Keywords: Deep Learning,NLP,CV,Transformers,MindSpore
Classifier: Intended Audience :: Developers
Classifier: License :: OSI Approved :: MIT License
Classifier: Operating System :: OS Independent
Classifier: Programming Language :: Python :: 3.7
Classifier: Programming Language :: Python :: 3.8
Classifier: Topic :: Text Processing
Classifier: Topic :: Scientific/Engineering :: Artificial Intelligence
Classifier: Topic :: Scientific/Engineering :: Image Processing
License-File: LICENSE
Requires-Dist: loguru
Requires-Dist: ujson
Requires-Dist: tqdm
Requires-Dist: scipy
Requires-Dist: scikit-learn
